encode_decode_vbm/__init__.py
encode_decode_vbm/decode.py
encode_decode_vbm/encode.py
encode_decode_vbm/funcs/b32.py
encode_decode_vbm/funcs/b64.py
encode_decode_vbm/funcs/salter.py
encode_decode_vbm/funcs/sha256.py
encode_decode_vbm/funcs/sha_funcs.py
encode_decode_vbm/funcs/vigenere.py
encode_decode_vbm-0.1.5.dist-info/METADATA
encode_decode_vbm-0.1.5.dist-info/WHEEL
encode_decode_vbm-0.1.5.dist-info/licenses/LICENSE
encode_decode_vbm-0.1.5.dist-info/RECORD
