Metadata-Version: 2.1
Name: encode_decode_vbm
Version: 0.1.5
Summary: encoding and decoding library for python
Project-URL: Homepage, https://github.com/mate12392/encode_decode_py
Author-email: Vidak-Becs Mate <matevidakbecs@gmail.com>
License-File: LICENSE
Classifier: License :: OSI Approved :: MIT License
Classifier: Operating System :: OS Independent
Classifier: Programming Language :: Python :: 3
Requires-Python: >=3.7
